httpsuite/RFC.py
httpsuite/__init__.py
httpsuite/http.py
httpsuite/interface.py
httpsuite-1.2.0.dist-info/AUTHORS
httpsuite-1.2.0.dist-info/LICENSE
httpsuite-1.2.0.dist-info/METADATA
httpsuite-1.2.0.dist-info/WHEEL
httpsuite-1.2.0.dist-info/pbr.json
httpsuite-1.2.0.dist-info/top_level.txt
httpsuite-1.2.0.dist-info/RECORD
