Metadata-Version: 2.1
Name: httpsuite
Version: 1.2.0
Summary: Collection of tools to parse, manipulate, and compile raw HTTP messages.
Home-page: https://github.com/shades-sh/httpsuite
Author: Felipe Faria
Author-email: felipefaria@hey.com
License: MIT
Project-URL: Bug Tracker, https://github.com/shades-sh/httpsuite/issues
Project-URL: Documentation, https://shades-sh.github.io/httpsuite/
Project-URL: Source Code, https://github.com/shades-sh/httpsuite/tree/master
Keywords: httpsuite,http,parser,validator
Platform: UNKNOWN
Classifier: Programming Language :: Python :: Implementation :: CPython
Classifier: Development Status :: 5 - Production/Stable
Classifier: License :: OSI Approved :: MIT License
Classifier: Natural Language :: English
Classifier: Topic :: Software Development :: Libraries
Classifier: Topic :: Utilities
Requires-Python: >=3.5
Requires-Dist: toolbox
Requires-Dist: dataclasses ; (python_version < '3.7')
Provides-Extra: dev
Requires-Dist: pytest ; extra == 'dev'
Requires-Dist: pytest-cov ; extra == 'dev'
Requires-Dist: coveralls ; extra == 'dev'
Requires-Dist: sphinx ; extra == 'dev'
Requires-Dist: sphinx-copybutton ; extra == 'dev'
Requires-Dist: sphinx-autobuild ; extra == 'dev'
Requires-Dist: m2r2 ; extra == 'dev'
Requires-Dist: furo ; extra == 'dev'
